odoo10_addon_shopinvader_locomotive_reset_password-10.0.1.1.0.99.dev4-py3.8-nspkg.pth
odoo/addons/shopinvader_locomotive_reset_password/README.rst
odoo/addons/shopinvader_locomotive_reset_password/__init__.py
odoo/addons/shopinvader_locomotive_reset_password/__manifest__.py
odoo/addons/shopinvader_locomotive_reset_password/data/ir_cron.xml
odoo/addons/shopinvader_locomotive_reset_password/data/mail_template.xml
odoo/addons/shopinvader_locomotive_reset_password/demo/shopinvader_backend.xml
odoo/addons/shopinvader_locomotive_reset_password/i18n/shopinvader_locomotive_reset_password.pot
odoo/addons/shopinvader_locomotive_reset_password/models/__init__.py
odoo/addons/shopinvader_locomotive_reset_password/models/partner.py
odoo/addons/shopinvader_locomotive_reset_password/models/shopinvader_backend.py
odoo/addons/shopinvader_locomotive_reset_password/readme/CONTRIBUTORS.rst
odoo/addons/shopinvader_locomotive_reset_password/readme/DESCRIPTION.rst
odoo/addons/shopinvader_locomotive_reset_password/services/__init__.py
odoo/addons/shopinvader_locomotive_reset_password/services/customer.py
odoo/addons/shopinvader_locomotive_reset_password/static/description/index.html
odoo/addons/shopinvader_locomotive_reset_password/tests/__init__.py
odoo/addons/shopinvader_locomotive_reset_password/tests/test_password_expired_reset.py
odoo/addons/shopinvader_locomotive_reset_password/views/partner_view.xml
odoo/addons/shopinvader_locomotive_reset_password/views/shopinvader_backend.xml
odoo/addons/shopinvader_locomotive_reset_password/wizards/__init__.py
odoo/addons/shopinvader_locomotive_reset_password/wizards/reset_password.py
odoo/addons/shopinvader_locomotive_reset_password/wizards/reset_password_view.xml
odoo10_addon_shopinvader_locomotive_reset_password-10.0.1.1.0.99.dev4.dist-info/METADATA
odoo10_addon_shopinvader_locomotive_reset_password-10.0.1.1.0.99.dev4.dist-info/WHEEL
odoo10_addon_shopinvader_locomotive_reset_password-10.0.1.1.0.99.dev4.dist-info/namespace_packages.txt
odoo10_addon_shopinvader_locomotive_reset_password-10.0.1.1.0.99.dev4.dist-info/top_level.txt
odoo10_addon_shopinvader_locomotive_reset_password-10.0.1.1.0.99.dev4.dist-info/RECORD
