Metadata-Version: 2.1
Name: odoo10-addon-shopinvader-locomotive-reset-password
Version: 10.0.1.1.0.99.dev4
Summary: Give the possibility to send a email to reset thepassword from odoo
Home-page: https://github.com/shopinvader/odoo-shopinvader
Author: Akretion
License: AGPL-3
Platform: UNKNOWN
Classifier: Programming Language :: Python
Classifier: Framework :: Odoo
Classifier: License :: OSI Approved :: GNU Affero General Public License v3
Requires-Python: ~=2.7
Requires-Dist: odoo10-addon-shopinvader-locomotive
Requires-Dist: odoo (<10.1dev,>=10.0)
